WeiXueyuanJavaJiaocheng/README.md
WeiXueyuanJavaJiaocheng/__init__.py
WeiXueyuanJavaJiaocheng/__main__.py
WeiXueyuanJavaJiaocheng/file.epub
WeiXueyuanJavaJiaocheng/index.html
WeiXueyuanJavaJiaocheng/css/__init__.py
WeiXueyuanJavaJiaocheng/css/annotations.css
WeiXueyuanJavaJiaocheng/css/main.css
WeiXueyuanJavaJiaocheng/css/normalize.css
WeiXueyuanJavaJiaocheng/css/popup.css
WeiXueyuanJavaJiaocheng/font/__init__.py
WeiXueyuanJavaJiaocheng/font/fontello.eot
WeiXueyuanJavaJiaocheng/font/fontello.svg
WeiXueyuanJavaJiaocheng/font/fontello.ttf
WeiXueyuanJavaJiaocheng/font/fontello.woff
WeiXueyuanJavaJiaocheng/img/__init__.py
WeiXueyuanJavaJiaocheng/img/annotator-glyph-sprite.png
WeiXueyuanJavaJiaocheng/img/annotator-icon-sprite.png
WeiXueyuanJavaJiaocheng/img/apple-touch-icon.png
WeiXueyuanJavaJiaocheng/img/cancelfullscreen.png
WeiXueyuanJavaJiaocheng/img/close.png
WeiXueyuanJavaJiaocheng/img/fullscreen.png
WeiXueyuanJavaJiaocheng/img/loader.gif
WeiXueyuanJavaJiaocheng/img/menu-icon.png
WeiXueyuanJavaJiaocheng/img/save.png
WeiXueyuanJavaJiaocheng/img/saved.png
WeiXueyuanJavaJiaocheng/img/settings-s.png
WeiXueyuanJavaJiaocheng/img/settings.png
WeiXueyuanJavaJiaocheng/img/star.png
WeiXueyuanJavaJiaocheng/js/__init__.py
WeiXueyuanJavaJiaocheng/js/epub.js
WeiXueyuanJavaJiaocheng/js/epub.min.js
WeiXueyuanJavaJiaocheng/js/epub.min.map
WeiXueyuanJavaJiaocheng/js/hooks.min.js
WeiXueyuanJavaJiaocheng/js/hooks.min.map
WeiXueyuanJavaJiaocheng/js/reader.js
WeiXueyuanJavaJiaocheng/js/reader.js.map
WeiXueyuanJavaJiaocheng/js/reader.min.js
WeiXueyuanJavaJiaocheng/js/reader.min.map
WeiXueyuanJavaJiaocheng/js/hooks/__init__.py
WeiXueyuanJavaJiaocheng/js/hooks/extensions/__init__.py
WeiXueyuanJavaJiaocheng/js/hooks/extensions/highlight.js
WeiXueyuanJavaJiaocheng/js/libs/__init__.py
WeiXueyuanJavaJiaocheng/js/libs/jquery.min.js
WeiXueyuanJavaJiaocheng/js/libs/localforage.min.js
WeiXueyuanJavaJiaocheng/js/libs/screenfull.js
WeiXueyuanJavaJiaocheng/js/libs/screenfull.min.js
wei_xueyuan_java_jiaocheng-2024.3.2.0.dist-info/METADATA
wei_xueyuan_java_jiaocheng-2024.3.2.0.dist-info/WHEEL
wei_xueyuan_java_jiaocheng-2024.3.2.0.dist-info/entry_points.txt
wei_xueyuan_java_jiaocheng-2024.3.2.0.dist-info/top_level.txt
wei_xueyuan_java_jiaocheng-2024.3.2.0.dist-info/RECORD
